straxrpc/__init__.py
straxrpc/client.py
straxrpc/config.py
straxrpc/data_types.py
straxrpc/server.py
straxrpc/straxrpc_client.py
straxrpc/straxrpc_pb2.py
straxrpc/straxrpc_pb2_grpc.py
straxrpc/straxrpc_server.py
straxrpc-0.3.dist-info/METADATA
straxrpc-0.3.dist-info/RECORD
straxrpc-0.3.dist-info/WHEEL
straxrpc-0.3.dist-info/top_level.txt
